universal_api_connector/__init__.py
universal_api_connector/app.py
universal_api_connector/auth_manager.py
universal_api_connector/credential_store.py
universal_api_connector/openapi_helper.py
universal_api_connector/utils.py
universal_api_connector-0.1.1.dist-info/LICENSE
universal_api_connector-0.1.1.dist-info/METADATA
universal_api_connector-0.1.1.dist-info/WHEEL
universal_api_connector-0.1.1.dist-info/top_level.txt
universal_api_connector-0.1.1.dist-info/RECORD
