Metadata-Version: 2.1
Name: universal-api-connector
Version: 0.1.1
Summary: Universal OpenAPI-driven API connector
Home-page: https://github.com/yourusername/universal-api-connector
Author: Your Name
Classifier: Programming Language :: Python :: 3
Classifier: License :: OSI Approved :: MIT License
Classifier: Operating System :: OS Independent
Requires-Python: >=3.7
License-File: LICENSE
Requires-Dist: requests
Requires-Dist: PyYAML
Requires-Dist: streamlit
Requires-Dist: requests-oauthlib
